README.rst
setup.cfg
setup.py
compute_gc/__init__.py
compute_gc.egg-info/PKG-INFO
compute_gc.egg-info/SOURCES.txt
compute_gc.egg-info/dependency_links.txt
compute_gc.egg-info/not-zip-safe
compute_gc.egg-info/requires.txt
compute_gc.egg-info/top_level.txt