Metadata-Version: 1.0
Name: compute-gc
Version: 1.0
Summary: Compute GC content of DNA sequences
Home-page: UNKNOWN
Author: Eunkyung Kim
Author-email: eunkyung@usc.edu
License: UNKNOWN
Platform: UNKNOWN
